eiapy.py
eiapy-0.1.6.dist-info/LICENSE.md
eiapy-0.1.6.dist-info/METADATA
eiapy-0.1.6.dist-info/WHEEL
eiapy-0.1.6.dist-info/top_level.txt
eiapy-0.1.6.dist-info/RECORD
