Metadata-Version: 2.1
Name: eiapy
Version: 0.1.6
Summary: A simple wrapper for the U.S. Energy Information Administration (EIA) API.
Home-page: https://github.com/systemcatch/eiapy
Author: Chris Brown
Author-email: cebrown999@gmail.com
License: MIT
Keywords: EIA Data API Energy
Platform: UNKNOWN
Classifier: Development Status :: 3 - Alpha
Classifier: Intended Audience :: Developers
Classifier: Intended Audience :: Science/Research
Classifier: Topic :: Scientific/Engineering :: Physics
Classifier: Natural Language :: English
Classifier: License :: OSI Approved :: MIT License
Classifier: Programming Language :: Python :: 3
Classifier: Programming Language :: Python :: 3.6
Classifier: Programming Language :: Python :: 3.7
Classifier: Programming Language :: Python :: 3.8
Classifier: Programming Language :: Python :: 3.9
Classifier: Programming Language :: Python :: 3.10
Requires-Python: >=3
License-File: LICENSE.md
Requires-Dist: requests
